{"weeks":{"2026-W29":{"TE|TV":106,"CENT|HOOD":15,"CENT|XRP":15,"HOOD|XRP":15,"BYND|GPRO":10,"BYND|SNAP":10,"GPRO|SNAP":10,"DD|DRS":20,"DD|GME":20,"DD|HF":20,"DD|ITM":20,"DD|RDDT":20,"DRS|GME":20,"DRS|HF":20,"DRS|ITM":20,"DRS|RDDT":20,"GME|HF":20,"GME|ITM":20,"GME|RDDT":20,"HF|ITM":20,"HF|RDDT":20,"ITM|RDDT":20,"LINK|MSTR":15,"HP|MA":4,"LINK|PUMP":10,"BLK|CME":8,"BLK|DRW":8,"BLK|GS":8,"BLK|MSFT":8,"CME|DRW":8,"CME|GS":14,"CME|MSFT":14,"DRW|GS":8,"DRW|MSFT":8,"GS|MSFT":14,"PATH|PUMP":14,"IBM|UBS":8,"NA|PL":1,"MBIN|MS":1,"BLK|UAA":1,"SBI|XRP":10,"DD|V":5,"DRS|V":5,"GME|V":5,"HF|V":5,"ITM|V":5,"RDDT|V":5,"ET|V":5,"ET|OTLK":1,"ET|PM":1,"ET|SPCX":1,"ET|UAL":1,"OTLK|PM":1,"OTLK|SPCX":1,"OTLK|UAL":1,"PM|SPCX":1,"PM|UAL":1,"SPCX|UAL":1,"ARKO|ENR":1,"SOXL|TE":6,"SOXL|TV":6,"SOXL|VTI":6,"TE|VTI":38,"TV|VTI":36,"DON|LINK":18,"DD|DON":12,"DON|DRS":12,"DON|GME":12,"DON|HF":12,"DON|ITM":12,"DON|RDDT":12,"DON|SPCX":7,"AMZN|HOOD":6,"OPEN|TE":3,"OPEN|TV":2,"OPEN|VTI":3,"AMAT|AVGO":2,"AMAT|BABA":2,"AVGO|BABA":2,"DON|HOOD":2,"SOXL|TQQQ":2,"DJT|NDAQ":2,"NDAQ|NFLX":1,"GLD|NDAQ":1,"GLD|SPY":1,"NDAQ|SPY":1,"NDAQ|PRAA":2,"QBTS|QUBT":1,"FNWD|NDAQ":1,"NDAQ|QQQX":1,"NDAQ|RJET":1,"GS|GTEK":1,"EAOM|ESG":1,"EAOM|ETHA":1,"EAOM|SLV":1,"ESG|ETHA":1,"ESG|SLV":1,"ETHA|SLV":1,"EVTV|NDAQ":1,"NDAQ|RPGL":1,"AGYTF|JAGX":1,"AGYTF|NDAQ":1,"JAGX|NDAQ":1,"NDAQ|QMCO":1,"NDAQ|QUBT":1,"QMCO|QUBT":1,"NDAQ|RBIL":1,"NDAQ|TIPS":1,"RBIL|TIPS":1,"NDAQ|PRFZ":1,"NDAQ|QQQ":1,"NDAQ|RAFI":1,"PRFZ|QQQ":1,"PRFZ|RAFI":1,"QQQ|RAFI":1,"FTGS|NDAQ":1,"DRAM|MU":10,"DRAM|SNDK":10,"DRAM|TE":10,"DRAM|TV":10,"MU|SNDK":10,"MU|TE":10,"MU|TV":10,"SNDK|TE":10,"SNDK|TV":10,"LINK|XRP":5,"DIS|DON":2,"DIS|LINK":2,"DIS|LOVE":2,"DIS|ORCL":2,"DON|LOVE":5,"DON|ORCL":5,"LINK|LOVE":10,"LINK|ORCL":5,"LOVE|ORCL":5,"COST|SPCX":5,"LINK|SAVE":4,"LOVE|SAVE":4,"CME|DOW":3,"DOW|GS":3,"DOW|MSFT":3,"CAT|HOOD":2,"CSAI|NDAQ":1,"DOW|NFLX":1,"APAC|OPEN":1,"AERO|ALBT":4,"AERO|BTC":4,"AERO|LUNA":4,"ALBT|BTC":4,"ALBT|LUNA":4,"BTC|LUNA":4,"SPCX|TSLA":4,"B|HOOD":1,"COST|LOW":1,"LOW|SAVE":1,"COST|DON":2,"CO|HP":2,"CO|MA":2,"CO|DD":1,"CO|DON":1,"CO|DRS":1,"CO|GME":1,"CO|HF":1,"CO|ITM":1,"CO|RDDT":1,"HR|UI":1,"RDDT|VOO":1,"LINK|SNAP":1,"LOVE|SNAP":1,"NDAQ|PICS":1,"NDAQ|V":1,"PICS|V":1},"2026-W30":{"DE|MA":2,"DE|PM":2,"MA|PM":6,"TE|TV":67,"TE|VTI":67,"TV|VTI":67,"DD|DRS":20,"DD|GME":20,"DD|HF":20,"DD|ITM":20,"DD|RDDT":20,"DRS|GME":20,"DRS|HF":20,"DRS|ITM":20,"DRS|RDDT":20,"GME|HF":20,"GME|ITM":20,"GME|RDDT":20,"HF|ITM":20,"HF|RDDT":20,"ITM|RDDT":20,"CENT|HOOD":14,"CENT|XRP":14,"HOOD|XRP":14,"BAC|EVER":5,"ED|ET":2,"RDDT|VOO":6,"EVER|MU":4,"EVER|NASA":4,"EVER|PM":4,"EVER|VGT":4,"EVER|VOO":4,"MU|NASA":4,"MU|PM":4,"MU|VGT":4,"MU|VOO":4,"NASA|PM":4,"NASA|VGT":4,"NASA|VOO":4,"PM|VGT":4,"PM|VOO":4,"VGT|VOO":4,"EVER|OPEN":5,"HOOD|TIME":4,"HOOD|WASH":4,"TIME|WASH":4,"OPEN|TV":3,"EVER|SPY":2,"EVER|LINK":2,"EVER|ORCL":2,"LINK|ORCL":2,"TE|TQQQ":1,"TQQQ|TV":1,"TQQQ|VTI":1,"INIO|LOW":1,"BTC|KYC":4,"HOOD|PUMP":1,"PUMP|TIME":1,"PUMP|WASH":1,"SPCX|SPGI":1,"DE|ET":1,"HUT|TXN":1,"CHTR|RY":1,"AMD|MSFT":1,"ASX|PSKY":1,"ASX|WBD":2,"PSKY|WBD":1,"COST|EVER":2,"SPCX|UPS":2,"MU|SNDK":1,"HOOD|XYZ":2,"COIN|ET":2,"COIN|EVER":1,"COIN|OPEN":2,"TDOT|TE":5,"TDOT|TV":5,"TDOT|VTI":5,"GOOG|GOOGL":1,"JPM|KRC":1,"CRWV|NBIS":4,"LIVE|TE":14,"LIVE|TV":14,"LIVE|VTI":14,"LIVE|TDOT":2,"COST|SELF":1,"BTC|XRP":2,"ET|FF":1,"NBIS|NVDA":1}}}